loadit/__about__.py
loadit/__init__.py
loadit/cache_base.py
loadit/dict_cache.py
loadit/loadit.py
loadit/sharded_dataset.py
loadit/util.py
loadit/writer.py
loadit-0.0.8.dist-info/METADATA
loadit-0.0.8.dist-info/WHEEL
loadit-0.0.8.dist-info/licenses/LICENSE.txt
loadit-0.0.8.dist-info/RECORD
