Metadata-Version: 2.3
Name: loadit
Version: 0.0.8
Summary: Easily convert iterables over large datasets into random access.
Project-URL: Documentation, https://github.com/acutkosky/loadit#readme
Project-URL: Issues, https://github.com/acutkosky/loadit/issues
Project-URL: Source, https://github.com/acutkosky/loadit
Author-email: Ashok Cutkosky <ashok@cutkosky.com>
License-Expression: MIT
License-File: LICENSE.txt
Classifier: Development Status :: 4 - Beta
Classifier: Programming Language :: Python
Classifier: Programming Language :: Python :: 3.7
Classifier: Programming Language :: Python :: 3.8
Classifier: Programming Language :: Python :: 3.9
Classifier: Programming Language :: Python :: 3.10
Classifier: Programming Language :: Python :: 3.11
Classifier: Programming Language :: Python :: Implementation :: CPython
Classifier: Programming Language :: Python :: Implementation :: PyPy
Requires-Python: >=3.7
Requires-Dist: filelock>=3.12.4
Requires-Dist: fsspec>=2023.9.2
Requires-Dist: watchdog>=3.0.0
Provides-Extra: dev
Requires-Dist: numpy>=1.26.0; extra == 'dev'
Requires-Dist: pytest>=7.4.0; extra == 'dev'
